expressdate/__init__.py
expressdate/date.py
expressdate/parse.py
expressdate-0.0.1.dist-info/LICENSE
expressdate-0.0.1.dist-info/METADATA
expressdate-0.0.1.dist-info/WHEEL
expressdate-0.0.1.dist-info/RECORD
