Metadata-Version: 2.1
Name: expressdate
Version: 0.0.1
Summary: Express-fast and flexible to express dates.
Home-page: https://github.com/DuelitDev/expressdate
License: MIT
Keywords: date,datetime,util,utility,utilities,dateutil,expressdate
Author: DuelitDev
Author-email: jyoon07dev@gmail.com
Requires-Python: >=3.10,<4.0
Classifier: License :: OSI Approved :: MIT License
Classifier: Programming Language :: Python :: 3
Classifier: Programming Language :: Python :: 3.10
Classifier: Programming Language :: Python :: 3.11
Classifier: Programming Language :: Python :: 3.12
Classifier: Programming Language :: Python :: 3.13
Classifier: Programming Language :: Python :: 3 :: Only
Project-URL: Repository, https://github.com/DuelitDev/expressdate
Project-URL: changelog, https://github.com/DuelitDev/expressdate/releases
Project-URL: download, https://github.com/DuelitDev/expressdate/tarball/master
Project-URL: documentation, https://github.com/DuelitDev/expressdate/wiki
Project-URL: homepage, https://github.com/DuelitDev/expressdate
Project-URL: issues, https://github.com/DuelitDev/expressdate/issues
